Harshit/BoolSet.py
Harshit/CharSet.py
Harshit/__init__.py
Harshit/anim.py
Harshit/maths.py
HarshitUtils-0.0.1.dist-info/LICENSE
HarshitUtils-0.0.1.dist-info/METADATA
HarshitUtils-0.0.1.dist-info/WHEEL
HarshitUtils-0.0.1.dist-info/top_level.txt
HarshitUtils-0.0.1.dist-info/RECORD
