Metadata-Version: 2.1
Name: HarshitUtils
Version: 0.0.1
Summary: Harshit
Author: Harshit Shrivastav
Author-email: itsharshit@yandex.com
Keywords: variables,math,strings,pyrogrammers,Harshit Shrivastav
Classifier: Development Status :: 1 - Planning
Classifier: Intended Audience :: Developers
Classifier: Programming Language :: Python :: 3
Classifier: Operating System :: MacOS :: MacOS X
Classifier: Operating System :: Microsoft :: Windows
License-File: LICENSE
